{
  "created_at": "2015-04-11 07:37:06+00:00",
  "n_members": 6709,
  "n_members_core": 31,
  "n_members_staged_recipes": 16,
  "n_repos": 25267,
  "n_issues": 35550,
  "n_open_issues": 5390,
  "n_closed_issues": 30160,
  "n_prs": 483124,
  "n_open_prs": 18464,
  "n_closed_prs": 464660,
  "downloads": {
    "month": "866683725",
    "year": "9248287787",
    "all": "25893670009"
  },
  "n_artifacts": 2389471,
  "n_packages": 29238,
  "n_platforms": 7,
  "n_commits": null,
  "n_commits_bots": null
}